{
 "actions": [],
 "allow_rename": 1,
 "creation": "2025-12-24 16:55:32.335607",
 "doctype": "DocType",
 "editable_grid": 1,
 "engine": "InnoDB",
 "field_order": [
  "issued_date",
  "issued_to",
  "to_machine",
  "for_component",
  "issued_location",
  "usage_info",
  "column_break_agcu",
  "transaction_id",
  "return_transaction_id",
  "returned_date",
  "returned_location",
  "returned_info",
  "status"
 ],
 "fields": [
  {
   "fieldname": "issued_date",
   "fieldtype": "Datetime",
   "label": "Issued Date"
  },
  {
   "fieldname": "issued_to",
   "fieldtype": "Link",
   "label": "Issued to",
   "options": "Work Force"
  },
  {
   "fieldname": "to_machine",
   "fieldtype": "Link",
   "label": "To Machine",
   "options": "Machine and Equipment List"
  },
  {
   "fieldname": "for_component",
   "fieldtype": "Link",
   "label": "For Component",
   "options": "Component"
  },
  {
   "fieldname": "issued_location",
   "fieldtype": "Link",
   "label": "Issued Location",
   "options": "Storage Location"
  },
  {
   "fieldname": "column_break_agcu",
   "fieldtype": "Column Break"
  },
  {
   "fieldname": "returned_date",
   "fieldtype": "Datetime",
   "label": "Returned Date"
  },
  {
   "fieldname": "returned_location",
   "fieldtype": "Link",
   "label": "Returned Location",
   "options": "Storage Location"
  },
  {
   "fieldname": "usage_info",
   "fieldtype": "Small Text",
   "label": "Usage info"
  },
  {
   "fieldname": "transaction_id",
   "fieldtype": "Data",
   "label": "Transaction ID"
  },
  {
   "fieldname": "return_transaction_id",
   "fieldtype": "Data",
   "label": "Return Transaction ID"
  },
  {
   "fieldname": "returned_info",
   "fieldtype": "Small Text",
   "label": "Returned Info"
  },
  {
   "fieldname": "status",
   "fieldtype": "Data",
   "label": "Status",
   "options": "\n"
  }
 ],
 "grid_page_length": 50,
 "index_web_pages_for_search": 1,
 "istable": 1,
 "links": [],
 "modified": "2026-01-13 18:57:51.809874",
 "modified_by": "Administrator",
 "module": "Plant Manager",
 "name": "Cutting Tool Usage Log",
 "owner": "Administrator",
 "permissions": [],
 "row_format": "Dynamic",
 "sort_field": "modified",
 "sort_order": "DESC",
 "states": []
}